healthcheck_extended/__init__.py
tests/__init__.py
tests/unit/__init__.py
tests/unit/test_healthcheck.py
healthcheck_extended-1.3.4.dist-info/LICENSE.txt
healthcheck_extended-1.3.4.dist-info/METADATA
healthcheck_extended-1.3.4.dist-info/WHEEL
healthcheck_extended-1.3.4.dist-info/top_level.txt
healthcheck_extended-1.3.4.dist-info/RECORD
