Metadata-Version: 2.1
Name: healthcheck-extended
Version: 1.3.4
Summary: Adds healthcheck endpoints to Flask apps
Home-page: https://github.com/schabi88/healthcheck-extended
Author: Felix Schabernack
Author-email: felix.schabernack@gmail.com
License: MIT
Platform: any
Classifier: Development Status :: 5 - Production/Stable
Classifier: Environment :: Web Environment
Classifier: Framework :: Flask
Classifier: Programming Language :: Python
Provides-Extra: dev
Requires-Dist: twine ; extra == 'dev'
Requires-Dist: wheel ; extra == 'dev'
Requires-Dist: setuptools-scm ; extra == 'dev'
Requires-Dist: setuptools-lint ; extra == 'dev'
Requires-Dist: requirements-builder ; extra == 'dev'
Provides-Extra: tests
Requires-Dist: flask ; extra == 'tests'
Requires-Dist: pylint ; extra == 'tests'
Requires-Dist: flake8 ; extra == 'tests'
